collectins/__init__.py
collectins/doublylinkedlist.py
collectins/linkedlist.py
collectins-0.1.0.dist-info/licenses/License
collectins-0.1.0.dist-info/METADATA
collectins-0.1.0.dist-info/WHEEL
collectins-0.1.0.dist-info/top_level.txt
collectins-0.1.0.dist-info/RECORD
