Metadata-Version: 2.4
Name: collectins
Version: 0.1.0
Summary: Pythonic data structures with indexing support using dunder methods
Author-email: Santosh Varma Addala <santoshvarma2166@gmail.com>
License: MIT
Project-URL: Homepage, https://github.com/santoshvarmaaddala/
Project-URL: Repository, https://github.com/santoshvarmaaddala/collectins
Keywords: data structures,indexing,dunder methods,ds,linked list,tree
Requires-Python: >=3.7
License-File: License
Dynamic: license-file
